esphome_dashboard/__init__.py
esphome_dashboard/base.template.html
esphome_dashboard/base_with_header_footer.template.html
esphome_dashboard/index.template.html
esphome_dashboard/login.template.html
esphome_dashboard/static/css/esphome-2.css
esphome_dashboard/static/firmware/bootloader.bin
esphome_dashboard/static/firmware/ota.bin
esphome_dashboard/static/firmware/partitions.bin
esphome_dashboard/static/fonts/codicon.ttf
esphome_dashboard/static/fonts/material-icons/LICENSE
esphome_dashboard/static/fonts/material-icons/MaterialIcons-Regular.woff
esphome_dashboard/static/fonts/material-icons/MaterialIcons-Regular.woff2
esphome_dashboard/static/fonts/material-icons/README.md
esphome_dashboard/static/fonts/material-icons/material-icons.css
esphome_dashboard/static/images/favicon.ico
esphome_dashboard/static/images/logo-text.svg
esphome_dashboard/static/js/esphome/c.-41e2Vua.js
esphome_dashboard/static/js/esphome/c.-41e2Vua.js.map
esphome_dashboard/static/js/esphome/c.9Q3Mj6jC.js
esphome_dashboard/static/js/esphome/c.9Q3Mj6jC.js.map
esphome_dashboard/static/js/esphome/c.B2LvkjpK.js
esphome_dashboard/static/js/esphome/c.B2LvkjpK.js.map
esphome_dashboard/static/js/esphome/c.B7LJSMzI.js
esphome_dashboard/static/js/esphome/c.B7LJSMzI.js.map
esphome_dashboard/static/js/esphome/c.BCuc9iMK.js
esphome_dashboard/static/js/esphome/c.BCuc9iMK.js.map
esphome_dashboard/static/js/esphome/c.BKawBtIt.js
esphome_dashboard/static/js/esphome/c.BKawBtIt.js.map
esphome_dashboard/static/js/esphome/c.BLbsWvxO.js
esphome_dashboard/static/js/esphome/c.BLbsWvxO.js.map
esphome_dashboard/static/js/esphome/c.BN-eppHo.js
esphome_dashboard/static/js/esphome/c.BN-eppHo.js.map
esphome_dashboard/static/js/esphome/c.BQYZTvuA.js
esphome_dashboard/static/js/esphome/c.BQYZTvuA.js.map
esphome_dashboard/static/js/esphome/c.BRQgpq1r.js
esphome_dashboard/static/js/esphome/c.BRQgpq1r.js.map
esphome_dashboard/static/js/esphome/c.BRm0uO7w.js
esphome_dashboard/static/js/esphome/c.BRm0uO7w.js.map
esphome_dashboard-20260110.0.dist-info/licenses/LICENSE
esphome_dashboard-20260110.0.dist-info/METADATA
esphome_dashboard-20260110.0.dist-info/WHEEL
esphome_dashboard-20260110.0.dist-info/top_level.txt
esphome_dashboard-20260110.0.dist-info/RECORD
