Metadata-Version: 2.4
Name: esphome-dashboard
Version: 20260110.0
Summary: ESPHome Device Builder
Home-page: https://github.com/esphome/dashboard
Author: Open Home Foundation
Author-email: hello@openhomefoundation.org
License: Apache-2.0
License-File: LICENSE
Dynamic: author
Dynamic: author-email
Dynamic: description
Dynamic: description-content-type
Dynamic: home-page
Dynamic: license
Dynamic: license-file
Dynamic: summary
